spinachlangapi/__init__.py
spinachlangapi/__main__.py
spinachlangapi/cli.py
spinachlangapi/main.py
spinachlangapi-0.1.0.dist-info/licenses/LICENSE
spinachlangapi-0.1.0.dist-info/METADATA
spinachlangapi-0.1.0.dist-info/WHEEL
spinachlangapi-0.1.0.dist-info/entry_points.txt
spinachlangapi-0.1.0.dist-info/top_level.txt
spinachlangapi-0.1.0.dist-info/RECORD
